{"number":76,"expires":{"notifications,f2f080e9-e858-49ae-8122-cba9baa4b9a7":1560028549929,"notifications,dd43e36e-16cf-44b6-92f8-70e68766b2ea":1560028549933},"notifications":{"f2f080e9-e858-49ae-8122-cba9baa4b9a7":{"create":{"type":"basic","iconUrl":"Icon.png","eventTime":1560028546328,"title":"hi there","message":"testing 123"},"data":{"title":"hi there","message":"testing 123","action":"createtab|https://example.com"},"expire":1560028549929,"id":"f2f080e9-e858-49ae-8122-cba9baa4b9a7"},"dd43e36e-16cf-44b6-92f8-70e68766b2ea":{"create":{"type":"image","iconUrl":"Icon.png","eventTime":1560028546333,"title":"Defend Zorah!","message":"Zorah is being raided!","buttons":[{"title":"Not Interested"}],"imageUrl":"https://t4.rbxcdn.com/292a5632bf53c25a318ea655171bfc86"},"data":{"title":"Defend Zorah!","image":"https://t4.rbxcdn.com/292a5632bf53c25a318ea655171bfc86","action":"createtab|https://www.roblox.com/games/714541439/BuildWorld-F3X-Alpha#!/game-instances?autoplay=true&server=2","message":"Zorah is being raided!","buttons":[{"title":"Not Interested"}]},"expire":1560028549933,"id":"dd43e36e-16cf-44b6-92f8-70e68766b2ea"}}}